<annotation>
	<folder>test</folder>
	<filename>Fresh Cucumber (99).jpg</filename>
	<path>C:\Users\nicot\Desktop\SIIL\img_concombre\concombre\test\Fresh Cucumber (99).jpg</path>
	<source>
		<database>Unknown</database>
	</source>
	<size>
		<width>512</width>
		<height>512</height>
		<depth>3</depth>
	</size>
	<segmented>0</segmented>
	<object>
		<name>concombre</name>
		<pose>Unspecified</pose>
		<truncated>0</truncated>
		<difficult>0</difficult>
		<bndbox>
			<xmin>107</xmin>
			<ymin>68</ymin>
			<xmax>359</xmax>
			<ymax>181</ymax>
		</bndbox>
	</object>
	<object>
		<name>concombre</name>
		<pose>Unspecified</pose>
		<truncated>0</truncated>
		<difficult>0</difficult>
		<bndbox>
			<xmin>61</xmin>
			<ymin>151</ymin>
			<xmax>397</xmax>
			<ymax>280</ymax>
		</bndbox>
	</object>
	<object>
		<name>concombre</name>
		<pose>Unspecified</pose>
		<truncated>0</truncated>
		<difficult>0</difficult>
		<bndbox>
			<xmin>99</xmin>
			<ymin>264</ymin>
			<xmax>346</xmax>
			<ymax>346</ymax>
		</bndbox>
	</object>
	<object>
		<name>concombre</name>
		<pose>Unspecified</pose>
		<truncated>0</truncated>
		<difficult>0</difficult>
		<bndbox>
			<xmin>91</xmin>
			<ymin>341</ymin>
			<xmax>355</xmax>
			<ymax>431</ymax>
		</bndbox>
	</object>
</annotation>
